stylegan2_torch/__init__.py
stylegan2_torch/discriminator/__init__.py
stylegan2_torch/discriminator/blocks.py
stylegan2_torch/equalized_lr.py
stylegan2_torch/generator/__init__.py
stylegan2_torch/generator/conv_block.py
stylegan2_torch/generator/mapping.py
stylegan2_torch/generator/rgb.py
stylegan2_torch/loss.py
stylegan2_torch/op/fused_act.py
stylegan2_torch/op/fused_bias_act.cpp
stylegan2_torch/op/fused_bias_act_kernel.cu
stylegan2_torch/op/upfirdn2d.cpp
stylegan2_torch/op/upfirdn2d.py
stylegan2_torch/op/upfirdn2d_kernel.cu
stylegan2_torch/utils.py
stylegan2_torch-1.3.0.dist-info/entry_points.txt
stylegan2_torch-1.3.0.dist-info/LICENSE
stylegan2_torch-1.3.0.dist-info/WHEEL
stylegan2_torch-1.3.0.dist-info/METADATA
stylegan2_torch-1.3.0.dist-info/RECORD
