Metadata-Version: 2.1
Name: stylegan2-torch
Version: 1.3.0
Summary: A simple, typed, commented Pytorch implementation of StyleGAN2.
Home-page: https://github.com/ppeetteerrs/stylegan2-torch
License: MIT
Author: Peter Yuen
Author-email: ppeetteerrsx@gmail.com
Requires-Python: >=3.8,<4.0
Classifier: License :: OSI Approved :: MIT License
Classifier: Programming Language :: Python :: 3
Classifier: Programming Language :: Python :: 3.10
Classifier: Programming Language :: Python :: 3.8
Classifier: Programming Language :: Python :: 3.9
Requires-Dist: torch (>=1.7.0)
Requires-Dist: torch-conv-gradfix (>=0.1.0)
Project-URL: Documentation, https://ppeetteerrs.github.io/stylegan2-torch
Project-URL: Repository, https://github.com/ppeetteerrs/stylegan2-torch
